openai_function/__init__.py
openai_function/chat_completion.py
openai_function/client.py
openai_function/faunadb/__init__.py
openai_function/faunadb/errors.py
openai_function/faunadb/objects.py
openai_function/faunadb/page.py
openai_function/faunadb/query.py
openai_function/fields.py
openai_function/json.py
openai_function/logging.py
openai_function/odm.py
openai_function/openai_functions.py
openai_function/store.py
openai_function/typedefs.py
openai_function-0.1.7.dist-info/METADATA
openai_function-0.1.7.dist-info/WHEEL
openai_function-0.1.7.dist-info/RECORD
