Metadata-Version: 2.1
Name: openai-function
Version: 0.1.7
Summary: 
Author: Oscar Bahamonde
Author-email: oscarmartinbahamondemunoz@gmail.com
Requires-Python: >=3.9,<4.0
Classifier: Programming Language :: Python :: 3
Classifier: Programming Language :: Python :: 3.9
Classifier: Programming Language :: Python :: 3.10
Classifier: Programming Language :: Python :: 3.11
Requires-Dist: aiohttp (>=3.8.5,<4.0.0)
Requires-Dist: iso8601 (>=2.0.0,<3.0.0)
Requires-Dist: numpy (>=1.25.1,<2.0.0)
Requires-Dist: openai (>=0.27.8,<0.28.0)
Requires-Dist: pydantic[dotenv] (==1.10.11)
Requires-Dist: rich (>=13.4.2,<14.0.0)
Requires-Dist: tiktoken (>=0.4.0,<0.5.0)
